cstr/__init__.py
cstr/ckpt/.gitkeep
cstr/cli.py
cstr/model/__init__.py
cstr/model/blocks.py
cstr/model/generative.py
cstr/predictor.py
cstr/preprocessor.py
cstr/utils/__init__.py
cstr/utils/annotating.py
cstr/utils/chem.py
cstr/utils/spectra.py
cstr-0.1.0.dist-info/LICENSE
cstr-0.1.0.dist-info/METADATA
cstr-0.1.0.dist-info/WHEEL
cstr-0.1.0.dist-info/entry_points.txt
cstr-0.1.0.dist-info/RECORD
