Metadata-Version: 2.1
Name: CSTR
Version: 0.1.0
Summary: Chemical Structure Transformer Ranker
License: MIT
Author: Yukai
Author-email: wangyk22@student.ubc.ca
Requires-Python: >=3.10,<3.13
Classifier: License :: OSI Approved :: MIT License
Classifier: Programming Language :: Python :: 3
Classifier: Programming Language :: Python :: 3.10
Classifier: Programming Language :: Python :: 3.11
Classifier: Programming Language :: Python :: 3.12
Requires-Dist: click (>=8.1.7,<9.0.0)
Requires-Dist: lightning (>=2.4.0,<3.0.0)
Requires-Dist: matchms (>=0.27.0,<0.28.0)
Requires-Dist: rdkit (>=2024.3.5,<2025.0.0)
Requires-Dist: torch (>=2.4.1,<3.0.0)
Requires-Dist: transformers (>=4.44.2,<5.0.0)
